discoss/__init__.py
discoss/data/video.py
discoss/sampler/__init__.py
discoss/sampler/bucketing.py
discoss/sampler/constraint.py
discoss/sampler/dynamic_bucketing.py
discoss/sampler/simple.py
discoss-0.1.1.dist-info/LICENSE
discoss-0.1.1.dist-info/METADATA
discoss-0.1.1.dist-info/WHEEL
discoss-0.1.1.dist-info/top_level.txt
discoss-0.1.1.dist-info/RECORD
