Metadata-Version: 2.1
Name: discoss
Version: 0.1.1
Summary: Distributed Coordinated Sequence Sampler
Home-page: https://github.com/lifeiteng/DiscoSeqSampler
Author: Feiteng Li
Author-email: lifeiteng0422@gmail.com
Maintainer: Feiteng Li
License: MIT
Project-URL: Homepage, https://github.com/lifeiteng/DiscoSeqSampler
Project-URL: Repository, https://github.com/lifeiteng/DiscoSeqSampler.git
Project-URL: Issues, https://github.com/lifeiteng/DiscoSeqSampler/issues
Keywords: distributed,sampling,sequence,coordination
Classifier: Development Status :: 3 - Alpha
Classifier: Intended Audience :: Developers
Classifier: Intended Audience :: Science/Research
Classifier: License :: OSI Approved :: MIT License
Classifier: Operating System :: OS Independent
Classifier: Programming Language :: Python :: 3
Classifier: Programming Language :: Python :: 3.10
Classifier: Programming Language :: Python :: 3.11
Classifier: Programming Language :: Python :: 3.12
Classifier: Topic :: Scientific/Engineering
Classifier: Topic :: Software Development :: Libraries :: Python Modules
Requires-Python: >=3.10
License-File: LICENSE
Provides-Extra: dev
Requires-Dist: pytest>=7.0; extra == "dev"
Requires-Dist: pytest-cov>=4.0; extra == "dev"
Requires-Dist: pytest-xdist>=3.0; extra == "dev"
Requires-Dist: black>=23.0; extra == "dev"
Requires-Dist: isort>=5.12; extra == "dev"
Requires-Dist: mypy>=1.5; extra == "dev"
Requires-Dist: pre-commit>=3.0; extra == "dev"
Requires-Dist: sphinx>=5.0; extra == "dev"
Requires-Dist: sphinx-rtd-theme>=1.0; extra == "dev"
Provides-Extra: docs
Requires-Dist: sphinx>=5.0; extra == "docs"
Requires-Dist: sphinx-rtd-theme>=1.0; extra == "docs"
Requires-Dist: myst-parser>=2.0; extra == "docs"
